sucolo_database_services-stubs/__init__.pyi
sucolo_database_services-stubs/data_access.pyi
sucolo_database_services-stubs/elasticsearch_client/__init__.pyi
sucolo_database_services-stubs/elasticsearch_client/index_manager.pyi
sucolo_database_services-stubs/elasticsearch_client/read_repository.pyi
sucolo_database_services-stubs/elasticsearch_client/service.pyi
sucolo_database_services-stubs/elasticsearch_client/write_repository.pyi
sucolo_database_services-stubs/redis_client/__init__.pyi
sucolo_database_services-stubs/redis_client/consts.pyi
sucolo_database_services-stubs/redis_client/keys_manager.pyi
sucolo_database_services-stubs/redis_client/read_repository.pyi
sucolo_database_services-stubs/redis_client/service.pyi
sucolo_database_services-stubs/redis_client/utils.pyi
sucolo_database_services-stubs/redis_client/write_repository.pyi
sucolo_database_services-stubs/services/__init__.pyi
sucolo_database_services-stubs/services/base_service.pyi
sucolo_database_services-stubs/services/data_management_service.pyi
sucolo_database_services-stubs/services/district_features_service.pyi
sucolo_database_services-stubs/services/dynamic_features_service.pyi
sucolo_database_services-stubs/services/fields_and_queries.pyi
sucolo_database_services-stubs/services/health_check_service.pyi
sucolo_database_services-stubs/services/metadata_service.pyi
sucolo_database_services-stubs/services/multiple_features_service.pyi
sucolo_database_services-stubs/tests/__init__.pyi
sucolo_database_services-stubs/tests/conftest.pyi
sucolo_database_services-stubs/tests/test_data_access.pyi
sucolo_database_services-stubs/tests/test_district_features_service.pyi
sucolo_database_services-stubs/utils/__init__.pyi
sucolo_database_services-stubs/utils/config.pyi
sucolo_database_services-stubs/utils/exceptions.pyi
sucolo_database_services-stubs/utils/polygons2hexagons.pyi
sucolo_database_services_stubs-0.4.3.dist-info/METADATA
sucolo_database_services_stubs-0.4.3.dist-info/WHEEL
sucolo_database_services_stubs-0.4.3.dist-info/RECORD
