Metadata-Version: 2.3
Name: sucolo-database-services-stubs
Version: 0.4.3
Summary: Type stubs for sucolo-database-services
License: MIT
Keywords: database,elasticsearch,redis,geospatial,typing,stubs
Author: Stanislaw Straburzynski
Author-email: sstraburzynski@gmail.com
Requires-Python: >=3.10,<3.14
Classifier: Development Status :: 4 - Beta
Classifier: Intended Audience :: Developers
Classifier: License :: OSI Approved :: MIT License
Classifier: Programming Language :: Python :: 3.10
Classifier: Programming Language :: Python :: 3.11
Classifier: Programming Language :: Python :: 3.12
Classifier: Programming Language :: Python :: 3.13
Classifier: Topic :: Database
Classifier: Topic :: Software Development :: Libraries :: Python Modules
Classifier: Typing :: Stubs Only
Requires-Dist: sucolo-database-services (>=0.2.0)
Project-URL: Documentation, https://github.com/Stashq/sucolo-database_services#readme
Project-URL: Homepage, https://github.com/Stashq/sucolo-database_services
Project-URL: Repository, https://github.com/Stashq/sucolo-database_services.git
